polyfiller_g4/__init__.py
polyfiller_g4-1.2.0.dist-info/LICENSE
polyfiller_g4-1.2.0.dist-info/METADATA
polyfiller_g4-1.2.0.dist-info/WHEEL
polyfiller_g4-1.2.0.dist-info/top_level.txt
polyfiller_g4-1.2.0.dist-info/RECORD
