Metadata-Version: 2.1
Name: polyfiller-g4
Version: 1.2.0
Summary: Polygon Filler
Home-page: https://github.com/Genzo4/polyfiller
Author: Genzo
Author-email: genzo@bk.ru
License: MIT
Project-URL: Bug Tracker, https://github.com/Genzo4/polyfiller/issues
Keywords: polyfiller,poly filler,polygon filler,opencv,opencv-contrib-python,g4
Classifier: Development Status :: 5 - Production/Stable
Classifier: Programming Language :: Python :: 3
Classifier: Programming Language :: Python :: 3.6
Classifier: Programming Language :: Python :: 3.7
Classifier: Programming Language :: Python :: 3.8
Classifier: Programming Language :: Python :: 3.9
Classifier: Programming Language :: Python :: 3.10
Classifier: Programming Language :: Python :: 3.11
Classifier: License :: OSI Approved :: MIT License
Classifier: Operating System :: OS Independent
Classifier: Intended Audience :: Developers
Classifier: Intended Audience :: Information Technology
Classifier: Natural Language :: English
Classifier: Natural Language :: Russian
Classifier: Topic :: Scientific/Engineering
Classifier: Topic :: Software Development
Classifier: Topic :: Software Development :: Libraries :: Python Modules
Requires-Python: >=3.6
License-File: LICENSE
Requires-Dist: opencv-contrib-python <4.6
Requires-Dist: numpy
Requires-Dist: utilspy-g4 >=2.2.0
